oxaudit/__init__.py
oxaudit/cli.py
oxaudit/scan.py
oxaudit-0.4.0.dist-info/METADATA
oxaudit-0.4.0.dist-info/WHEEL
oxaudit-0.4.0.dist-info/entry_points.txt
oxaudit-0.4.0.dist-info/top_level.txt
oxaudit-0.4.0.dist-info/RECORD
