Metadata-Version: 2.1
Name: oxaudit
Version: 0.4.0
Summary: A Python package to scan Solidity contracts using Oxaudit
Home-page: https://github.com/yourusername/oxaudit
Author: Your Name
Author-email: your.email@example.com
Classifier: Programming Language :: Python :: 3
Classifier: License :: OSI Approved :: MIT License
Classifier: Operating System :: OS Independent
Requires-Dist: requests
